nonebot_plugin_blacklist/__init__.py
nonebot_plugin_blacklist-1.4.3.dist-info/LICENSE
nonebot_plugin_blacklist-1.4.3.dist-info/METADATA
nonebot_plugin_blacklist-1.4.3.dist-info/WHEEL
nonebot_plugin_blacklist-1.4.3.dist-info/RECORD
