Metadata-Version: 2.1
Name: nonebot-plugin-blacklist
Version: 1.4.3
Summary: Blacklist in NoneBot2
Home-page: https://github.com/tkgs0/nonebot-plugin-blacklist
License: MIT
Keywords: nonebot,blacklist
Author: 月ヶ瀬
Requires-Python: >=3.9,<4.0
Classifier: License :: OSI Approved :: MIT License
Classifier: Programming Language :: Python :: 3
Classifier: Programming Language :: Python :: 3.9
Classifier: Programming Language :: Python :: 3.10
Classifier: Programming Language :: Python :: 3.11
Classifier: Programming Language :: Python :: 3.12
Requires-Dist: nonebot-adapter-onebot (>=2.4.1,<3.0.0)
Requires-Dist: nonebot2 (>=2.3.1,<3.0.0)
Requires-Dist: ujson (>=5.2.0)
Project-URL: Repository, https://github.com/tkgs0/nonebot-plugin-blacklist
